{
    "title": "Rentabilité solaire dans le Nord de la France : Mythe ou Réalité ?",
    "date": "2024-11-20",
    "category": "Guide",
    "summary": "Pas besoin d'habiter à Nice pour que le solaire soit rentable. Démonstration chiffrée.",
    "content": "<p>C'est une idée reçue tenace : il faudrait du soleil 365 jours par an pour rentabiliser des panneaux. C'est faux.</p><h3>La lumière suffit</h3><p>Les panneaux photovoltaïques modernes fonctionnent avec la luminosité, pas la chaleur. En fait, une chaleur excessive (comme dans le Sud en canicule) réduit leur rendement !</p><h3>Les chiffres du Nord</h3><p>À Lille, une installation de 3kWc produit environ 2900 à 3100 kWh par an. Avec un prix de l'électricité à 0,25€/kWh, cela représente plus de 700€ d'économies annuelles. Le retour sur investissement se fait généralement entre 8 et 10 ans, ce qui reste excellent pour un équipement durant 30 ans.</p>"
}